pipton/__init__.py
pipton/core.py
pipton/pipton_repl.py
pipton/repl.py
pipton/run_pipton.py
pipton/runner.py
pipton-2.0.0.dist-info/METADATA
pipton-2.0.0.dist-info/WHEEL
pipton-2.0.0.dist-info/entry_points.txt
pipton-2.0.0.dist-info/top_level.txt
pipton-2.0.0.dist-info/RECORD
