Metadata-Version: 2.1
Name: pipton
Version: 2.0.0
Summary: A custom language with Persian-flavored syntax and full Python power
Home-page: https://github.com/amirhossinpython/pipton_lang
Author: AmirhosseinPython
Author-email: amirhossinpython03@gmail.com
Classifier: Programming Language :: Python :: 3
Classifier: License :: OSI Approved :: MIT License
Classifier: Operating System :: OS Independent
Classifier: Topic :: Software Development :: Interpreters
Classifier: Intended Audience :: Developers
Classifier: Natural Language :: Persian
Requires-Python: >=3.6
